secure_package_template/__init__.py
secure_package_template/_version.py
secure_package_template/py.typed
secure_package_template-0.7.1.dist-info/METADATA
secure_package_template-0.7.1.dist-info/WHEEL
secure_package_template-0.7.1.dist-info/licenses/LICENSE
secure_package_template-0.7.1.dist-info/RECORD
