Metadata-Version: 2.1
Name: secure_package_template
Version: 0.7.1
Summary: Template for a Python package with a secure project host and package repository configuration.
Project-URL: Source, https://github.com/sethmlarson/secure-python-package-template
Author-email: Seth Michael Larson <sethmichaellarson@gmail.com>
License: This is free and unencumbered software released into the public domain.
License-File: LICENSE
Requires-Python: <4,>=3.7
